odoo/addons/customer_outstanding_statement/README.rst
odoo/addons/customer_outstanding_statement/__init__.py
odoo/addons/customer_outstanding_statement/__manifest__.py
odoo/addons/customer_outstanding_statement/i18n/ca.po
odoo/addons/customer_outstanding_statement/i18n/customer_outstanding_statement.pot
odoo/addons/customer_outstanding_statement/i18n/de.po
odoo/addons/customer_outstanding_statement/i18n/es.po
odoo/addons/customer_outstanding_statement/i18n/fr.po
odoo/addons/customer_outstanding_statement/i18n/hr_HR.po
odoo/addons/customer_outstanding_statement/i18n/it.po
odoo/addons/customer_outstanding_statement/i18n/nl.po
odoo/addons/customer_outstanding_statement/i18n/nl_NL.po
odoo/addons/customer_outstanding_statement/i18n/pt.po
odoo/addons/customer_outstanding_statement/i18n/ro.po
odoo/addons/customer_outstanding_statement/report/__init__.py
odoo/addons/customer_outstanding_statement/report/customer_outstanding_statement.py
odoo/addons/customer_outstanding_statement/static/description/Outstanding_Statement.png
odoo/addons/customer_outstanding_statement/static/description/icon.png
odoo/addons/customer_outstanding_statement/static/description/index.html
odoo/addons/customer_outstanding_statement/static/src/less/layout_statement.less
odoo/addons/customer_outstanding_statement/tests/__init__.py
odoo/addons/customer_outstanding_statement/tests/test_customer_outstanding_statement.py
odoo/addons/customer_outstanding_statement/views/statement.xml
odoo/addons/customer_outstanding_statement/wizard/__init__.py
odoo/addons/customer_outstanding_statement/wizard/customer_outstanding_statement_wizard.py
odoo/addons/customer_outstanding_statement/wizard/customer_outstanding_statement_wizard.xml
odoo11_addon_customer_outstanding_statement-11.0.2.1.2.dist-info/METADATA
odoo11_addon_customer_outstanding_statement-11.0.2.1.2.dist-info/RECORD
odoo11_addon_customer_outstanding_statement-11.0.2.1.2.dist-info/WHEEL
odoo11_addon_customer_outstanding_statement-11.0.2.1.2.dist-info/top_level.txt
